sentence_splitter/__init__.py
sentence_splitter/non_breaking_prefixes/ca.txt
sentence_splitter/non_breaking_prefixes/cs.txt
sentence_splitter/non_breaking_prefixes/da.txt
sentence_splitter/non_breaking_prefixes/de.txt
sentence_splitter/non_breaking_prefixes/el.txt
sentence_splitter/non_breaking_prefixes/en.txt
sentence_splitter/non_breaking_prefixes/es.txt
sentence_splitter/non_breaking_prefixes/fi.txt
sentence_splitter/non_breaking_prefixes/fr.txt
sentence_splitter/non_breaking_prefixes/hu.txt
sentence_splitter/non_breaking_prefixes/is.txt
sentence_splitter/non_breaking_prefixes/it.txt
sentence_splitter/non_breaking_prefixes/lt.txt
sentence_splitter/non_breaking_prefixes/lv.txt
sentence_splitter/non_breaking_prefixes/nl.txt
sentence_splitter/non_breaking_prefixes/no.txt
sentence_splitter/non_breaking_prefixes/pl.txt
sentence_splitter/non_breaking_prefixes/pt.txt
sentence_splitter/non_breaking_prefixes/ro.txt
sentence_splitter/non_breaking_prefixes/ru.txt
sentence_splitter/non_breaking_prefixes/sk.txt
sentence_splitter/non_breaking_prefixes/sl.txt
sentence_splitter/non_breaking_prefixes/sv.txt
sentence_splitter/non_breaking_prefixes/tr.txt
sentence_splitter-1.4.dist-info/LICENSE
sentence_splitter-1.4.dist-info/METADATA
sentence_splitter-1.4.dist-info/WHEEL
sentence_splitter-1.4.dist-info/top_level.txt
sentence_splitter-1.4.dist-info/RECORD
